Metadata-Version: 2.1
Name: argument-clinic
Version: 0.11
Summary: Argument clinic makes creates a command line interface out of your main() so you don't have to.
Home-page: https://github.com/DOsinga/argument-clinic
Author: Douwe Osinga
Author-email: douwe.osinga@gmail.com
License: MIT License
Platform: UNKNOWN
Classifier: Development Status :: 3 - Alpha
Classifier: Intended Audience :: Developers
Classifier: Natural Language :: English
Classifier: License :: OSI Approved :: Apache Software License
Classifier: Programming Language :: Python
Classifier: Programming Language :: Python :: 3
Classifier: Programming Language :: Python :: 3.6
Classifier: Programming Language :: Python :: 3.7
Classifier: Programming Language :: Python :: Implementation :: CPython
Classifier: Programming Language :: Python :: Implementation :: PyPy
Requires-Python: >=3.6
